{
  "stats": {
    "minecraft:mined": {
      "minecraft:obsidian": 2
    },
    "minecraft:picked_up": {
      "minecraft:obsidian": 2
    },
    "minecraft:used": {
      "minecraft:diamond_pickaxe": 2,
      "minecraft:obsidian": 1
    },
    "minecraft:custom": {
      "minecraft:jump": 9,
      "minecraft:time_since_rest": 743,
      "minecraft:leave_game": 1,
      "minecraft:sprint_one_cm": 1104,
      "minecraft:play_time": 743,
      "minecraft:time_since_death": 743,
      "minecraft:walk_one_cm": 1759,
      "minecraft:total_world_time": 782,
      "minecraft:fall_one_cm": 209,
      "minecraft:fly_one_cm": 1236
    }
  },
  "DataVersion": 3839
}